[
    {
      "title": "Spin and Sculpt",
      "date": "Jan. 13, 2025 - April 28, 2025",
      "time": "5:15 p.m. - 6:15 p.m.",
      "location": "Rec Center, Room 203, 202 Lindahl Dr., Wayne, NE 68787",
      "category": "FITNESS/RECREATION, EVENTS CALENDAR",
      "description": "Spring 2025 Spin and Sculpt classes are Mondays at 5:15 p.m."
    },
    {
      "title": "Yoga",
      "date": "Jan. 14, 2025 - April 29, 2025",
      "time": "5:15 p.m. - 6:00 p.m.",
      "location": "Rec Center, Room 106, 202 Lindahl Dr., Wayne, NE 68787",
      "category": "FITNESS/RECREATION, EVENTS CALENDAR",
      "description": "Spring 2025 Yoga classes are Tuesdays at 5:15 p.m."
    },
    {
      "title": "Killer Kettlebells",
      "date": "Jan. 14, 2025 - April 29, 2025",
      "time": "4:30 p.m. - 5:00 p.m.",
      "location": "Rec Center, Room 106, 202 Lindahl Dr., Wayne, NE 68787",
      "category": "FITNESS/RECREATION, EVENTS CALENDAR",
      "description": "Spring 2025 Killer Kettlebell classes are Tuesdays at 4:30 p.m."
    }
  ]
  